[
  {
    "title": "Учебники и книги для школьников",
    "description": "Здесь должен быть пояснительный текст Можно про издательство, мжно написать цену “от”..",
    "imageSrc": "./assets/images/girl-with-book.png"
  },
  {
    "title": "Учебные пособия для учителей и школ",
    "description": "Здесь должен быть пояснительный текст Можно про издательство, мжно написать цену “от”..",
    "imageSrc": "./assets/images/teacher.png"
  },
  {
    "title": "Литература для педагогов и воспитателей детсадов",
    "description": "Здесь должен быть пояснительный текст Можно про издательство, мжно написать цену “от”..",
    "imageSrc": "./assets/images/mentor.png"
  }
]
